setup.py
cryptoconditions/__init__.py
cryptoconditions/condition.py
cryptoconditions/crypto.py
cryptoconditions/exceptions.py
cryptoconditions/fulfillment.py
cryptoconditions/type_registry.py
cryptoconditions/version.py
cryptoconditions.egg-info/PKG-INFO
cryptoconditions.egg-info/SOURCES.txt
cryptoconditions.egg-info/dependency_links.txt
cryptoconditions.egg-info/requires.txt
cryptoconditions.egg-info/top_level.txt
cryptoconditions.egg-info/zip-safe
cryptoconditions/lib/__init__.py
cryptoconditions/lib/hasher.py
cryptoconditions/lib/predictor.py
cryptoconditions/lib/reader.py
cryptoconditions/lib/writer.py
cryptoconditions/types/__init__.py
cryptoconditions/types/base_sha256.py
cryptoconditions/types/ed25519.py
cryptoconditions/types/inverted_threshold_sha256.py
cryptoconditions/types/sha256.py
cryptoconditions/types/threshold_sha256.py
cryptoconditions/types/timeout.py