Metadata-Version: 1.1
Name: cryptoconditions
Version: 0.5.1
Summary: Multi-algorithm, multi-level, multi-signature format for expressing conditions and fulfillments according to the Interledger Protocol (ILP).
Home-page: https://github.com/bigchaindb/cryptoconditions/
Author: Cryptoconditions Contributors
Author-email: dev@bigchaindb.com
License: MIT
Keywords: cryptoconditions,interledger,merkle tree,ed25519,threshold signatures,hash lock
Platform: UNKNOWN
Classifier: Development Status :: 3 - Alpha
Classifier: Intended Audience :: Developers
Classifier: Topic :: Database
Classifier: Topic :: Database :: Database Engines/Servers
Classifier: Topic :: Software Development
Classifier: Natural Language :: English
Classifier: License :: OSI Approved :: MIT License
Classifier: Programming Language :: Python :: 3 :: Only
Classifier: Programming Language :: Python :: 3.4
Classifier: Programming Language :: Python :: 3.5
Classifier: Operating System :: MacOS :: MacOS X
Classifier: Operating System :: POSIX :: Linux
